Workbook

Sheet Instrucciones
A1: Consolidador de Facturación Mensual — Brasil / China / Alemania / Indonesia
A3: Cómo usar este archivo cada fin de mes:
A4: 1. Pestaña 'Brasil': borra la fila de ejemplo (fondo amarillo) y pega debajo los datos del mes tal como llegan de Brasil,
A5: respetando las columnas: Proforma, Tscode, Cliente, Qty, Ipcode, Description, Sales force, Price USD.
A6: 2. Pestaña 'Suiza_DE_CN_ID': borra la fila de ejemplo y pega los datos del archivo que envía Suiza (agrupa Alemania,
A7: China e Indonesia), respetando las columnas: cliente, pf, Ip Code, Description, Brand Line, Quantity, Net Price,
A8: Amount, Goods Origin. La columna 'Tscode (automático)' NO se pega: se autocompleta sola buscando el nombre de
A9: 'cliente' en la columna Alias de la pestaña 'Mercados'. Si un cliente nuevo no aparece, agrégalo ahí (ver punto 6).
A10: 3. La pestaña 'Consolidado' se arma sola con fórmulas. NO está protegida a propósito, para poder armar tablas
A11: dinámicas y gráficos directamente sobre ella. Por eso mismo no la edites/arrastres/borres filas a mano ahí
A12: (rompe las fórmulas) — para otra vista, créala en una pestaña nueva. Para borrar la fila de ejemplo en 'Brasil'
A13: o 'Suiza_DE_CN_ID': selecciona las celdas y presiona Supr/Delete. NO uses clic derecho > 'Eliminar fila'
... A32: Si muestra 'Revisar Ip Code' en Category/R-C/Mks description, el Ip Code no está en 'Gamma_Catalogo' (código nuevo o catálogo desactualizado).

Sheet Mercados
A1: Tscode | B1: Alias | C1: Mercado
A2: 0007510593 | C2: 774 - CHILE
A3: TS01683 | C3: 776 - CENTRAL AMERICA
A4: TS01696 | B4: PETIN | C4: 779 - URUGUAY
A5: TS01790 | C5: 774 - CHILE
A6: TS01886 | B6: YAMAHA | C6: 773 - COLOMBIA
A7: TS01916 | B7: ITALCAUCHOS | C7: 777 - ECUADOR
A8: TS01927 | B8: AUTOCENTRO | C8: 780 - PARAGUAY
A9: TS01928 | B9: CENEU | C9: 780 - PARAGUAY
A10: TS01932 | B10: DESERT | C10: 781 - PERU'
A11: TS02378 | B11: ISN S. | C11: 776 - CENTRAL AMERICA
A12: TS02414 | B12: MOTORALMOR | C12: 777 - ECUADOR
A13: TS02459 | B13: FAHONDA | C13: 776 - CENTRAL AMERICA
A14: TS02472 | B14: AKT | C14: 773 - COLOMBIA
A15: TS02592 | B15: MOAUTO | C15: 776 - CENTRAL AMERICA
A16: TS02793 | B16: AUTECO | C16: 773 - COLOMBIA
A17: TS02804 | C17: 776 - CENTRAL AMERICA
A18: TS02815 | B18: GEES | C18: 773 - COLOMBIA
A19: TS02816 | B19: ROLPARTS | C19: 773 - COLOMBIA
A20: TS02839 | B20: RENDILLANTAS | C20: 776 - CENTRAL AMERICA
A21: TS02840 | C21: 776 - CENTRAL AMERICA
A22: TS02845 | C22: 776 - CENTRAL AMERICA
A23: TS02848 | B23: PRESTIGE | C23: 776 - CENTRAL AMERICA
A24: TS02849 | C24: 788 - OTHER CARIBE
A25: TS02850 | C25: 788 - OTHER CARIBE
A26: TS02861 | B26: INTEGRANDO | C26: 773 - COLOMBIA
A27: TS02862 | C27: 773 - COLOMBIA
A28: TS02865 | B28: BRIFABRI | C28: 781 - PERU'
A29: TS03434 | B29: FANALCA | C29: 773 - COLOMBIA
A30: TS06007 | B30: MULTILLANTA | C30: 782 - BOLIVIA
A31: TS06039 | C31: 774 - CHILE
A32: TS06035 | C32: 788 - OTHER CARIBE

Sheet Gamma_Catalogo
A1: Catálogo de productos Gamma (referencia — actualizar cuando llegue versión nueva)
A2: Ip Code | B2: Description | C2: R/C | D2: Category | E2: Mks description
A3: 109200 | B3: 2.75-16 46P REINF Block C | C3: C | D3: COMMUTING | E3: COMMUTING
A4: 109400 | B4: 3.00-16REINF 48P(C) Block | C4: C | D4: COMMUTING | E4: COMMUTING
A5: 109500 | B5: 3.25-16 55P REINF Block C | C5: C | D5: COMMUTING | E5: COMMUTING
A6: 109700 | B6: 4.00-18 64P Block K | C6: C | D6: COMMUTING | E6: COMMUTING
A7: 109800 | B7: 3.00-19 54P REINF Block C | C7: C | D7: COMMUTING | E7: COMMUTING
A8: 109900 | B8: 3.25-19 54P Block C | C8: C | D8: COMMUTING | E8: COMMUTING
A9: 110000 | B9: 3.50-19 57P Block C | C9: C | D9: COMMUTING | E9: COMMUTING
A10: 110100 | B10: 4.00-18 64H Block C TOURING SPEC | C10: C | D10: COMMUTING | E10: COMMUTING
A11: 111100 | B11: 3.25-19TL 54S ME11 | C11: C | D11: COMMUTING | E11: COMMUTING
A12: 111700 | B12: 3.25-18 52H ME11 | C12: C | D12: COMMUTING | E12: COMMUTING
A13: 113700 | B13: 3.25-18REINF 59P ME22 | C13: C | D13: COMMUTING | E13: COMMUTING
A14: 116100 | B14: 3.00-17REINF 50PF&R ME22 | C14: C | D14: COMMUTING | E14: COMMUTING
... A1451: 4851200 | B1451: 180/55ZR17M/CTL (73W) (C) AnGT3R | C1451: R | D1451: RADIAL ZR | E1451: SPORT TOURING RADIAL

Sheet Brasil
A1: Proforma | B1: Tscode | C1: Cliente | D1: Qty | E1: Ipcode | F1: Description | G1: Sales force | H1: Price USD
A2: 7530016455 | B2: TS01916 | C2: ITALCAUCHOS C.L. (EJEMPLO - BORRAR) | D2: 19 | E2: 1342900 | F2: 110/70-17M/CTL 54H SpDemF | G2: 11386369 | H2: 38.34

Sheet Suiza_DE_CN_ID
A1: cliente | B1: Tscode (automático) | C1: pf | D1: Ip Code | E1: Description | F1: Brand Line | G1: Quantity | H1: Net Price | I1: Amount | J1: Goods Origin
A2: akt | B2: =IF(A2="","",IFERROR(INDEX(Mercados!$A$2:$A$32,MATCH(A2,Mercados!$B$2:$B$32,0)),"Revisar alias")) -> TS02472 | C2: 1730134137 | D2: 2283700 | E2: 180/55ZR17M/CTL (73W)(M) Z8-R | F2: Moto METZELER | G2: 3 | H2: 102 | I2: 327.3 | J2: CN
B3: =IF(A3="","",IFERROR(INDEX(Mercados!$A$2:$A$32,MATCH(A3,Mercados!$B$2:$B$32,0)),"Revisar alias"))
B4: =IF(A4="","",IFERROR(INDEX(Mercados!$A$2:$A$32,MATCH(A4,Mercados!$B$2:$B$32,0)),"Revisar alias"))
B5: =IF(A5="","",IFERROR(INDEX(Mercados!$A$2:$A$32,MATCH(A5,Mercados!$B$2:$B$32,0)),"Revisar alias"))
B6: =IF(A6="","",IFERROR(INDEX(Mercados!$A$2:$A$32,MATCH(A6,Mercados!$B$2:$B$32,0)),"Revisar alias"))
B7: =IF(A7="","",IFERROR(INDEX(Mercados!$A$2:$A$32,MATCH(A7,Mercados!$B$2:$B$32,0)),"Revisar alias"))
B8: =IF(A8="","",IFERROR(INDEX(Mercados!$A$2:$A$32,MATCH(A8,Mercados!$B$2:$B$32,0)),"Revisar alias"))
B9: =IF(A9="","",IFERROR(INDEX(Mercados!$A$2:$A$32,MATCH(A9,Mercados!$B$2:$B$32,0)),"Revisar alias"))
B10: =IF(A10="","",IFERROR(INDEX(Mercados!$A$2:$A$32,MATCH(A10,Mercados!$B$2:$B$32,0)),"Revisar alias"))
B11: =IF(A11="","",IFERROR(INDEX(Mercados!$A$2:$A$32,MATCH(A11,Mercados!$B$2:$B$32,0)),"Revisar alias"))
B12: =IF(A12="","",IFERROR(INDEX(Mercados!$A$2:$A$32,MATCH(A12,Mercados!$B$2:$B$32,0)),"Revisar alias"))
B13: =IF(A13="","",IFERROR(INDEX(Mercados!$A$2:$A$32,MATCH(A13,Mercados!$B$2:$B$32,0)),"Revisar alias"))
B14: =IF(A14="","",IFERROR(INDEX(Mercados!$A$2:$A$32,MATCH(A14,Mercados!$B$2:$B$32,0)),"Revisar alias"))
... B451: =IF(A451="","",IFERROR(INDEX(Mercados!$A$2:$A$32,MATCH(A451,Mercados!$B$2:$B$32,0)),"Revisar alias"))

Sheet Consolidado
A1: mercado | B1: cliente | C1: pf | D1: Ip Code | E1: Description | F1: Quantity | G1: FAC | H1: SEP | I1: Net Price | J1: Amount | K1: Goods Origin | L1: Category | M1: R/C | N1: Mks description | O1: Fuente
A2: =IF(Brasil!C2="","",IFERROR(INDEX(Mercados!$C$2:$C$32,MATCH(Brasil!B2,Mercados!$A$2:$A$32,0)),"Revisar Tscode")) -> 777 - ECUADOR | B2: =IF(Brasil!C2="","",Brasil!C2) -> ITALCAUCHOS C.L. (EJEMPLO - BORRAR) | C2: =IF(Brasil!C2="","",Brasil!A2) -> 7530016455 | D2: =IF(Brasil!C2="","",Brasil!E2) -> 1342900 | E2: =IF(Brasil!C2="","",Brasil!F2) -> 110/70-17M/CTL 54H SpDemF | F2: =IF(Brasil!C2="","",Brasil!D2) -> 19 | I2: =IF(Brasil!C2="","",Brasil!H2) -> 38.34 | J2: =IF(Brasil!C2="","",Brasil!D2*Brasil!H2) -> 728.46 | K2: =IF(Brasil!C2="","","BR") -> BR | L2: =IF(Brasil!C2="","",IFERROR(INDEX(Gamma_Catalogo!$D$3:$D$1451,MATCH(Brasil!E2,Gamma_Catalogo!$A$3:$A$1451,0)),"Revisar Ip Code")) -> MIX XPLY | M2: =IF(Brasil!C2="","",IFERROR(INDEX(Gamma_Catalogo!$C$3:$C$1451,MATCH(Brasil!E2,Gamma_Catalogo!$A$3:$A$1451,0)),"Revisar Ip Code")) -> C | N2: =IF(Brasil!C2="","",IFERROR(INDEX(Gamma_Catalogo!$E$3:$E$1451,MATCH(Brasil!E2,Gamma_Catalogo!$A$3:$A$1451,0)),"Revisar Ip Code")) -> SPORT TOURING X-PLY | O2: =IF(Brasil!C2="","","Brasil") -> Brasil
A3: =IF(Brasil!C3="","",IFERROR(INDEX(Mercados!$C$2:$C$32,MATCH(Brasil!B3,Mercados!$A$2:$A$32,0)),"Revisar Tscode")) | B3: =IF(Brasil!C3="","",Brasil!C3) | C3: =IF(Brasil!C3="","",Brasil!A3) | D3: =IF(Brasil!C3="","",Brasil!E3) | E3: =IF(Brasil!C3="","",Brasil!F3) | F3: =IF(Brasil!C3="","",Brasil!D3) | I3: =IF(Brasil!C3="","",Brasil!H3) | J3: =IF(Brasil!C3="","",Brasil!D3*Brasil!H3) | K3: =IF(Brasil!C3="","","BR") | L3: =IF(Brasil!C3="","",IFERROR(INDEX(Gamma_Catalogo!$D$3:$D$1451,MATCH(Brasil!E3,Gamma_Catalogo!$A$3:$A$1451,0)),"Revisar Ip Code")) | M3: =IF(Brasil!C3="","",IFERROR(INDEX(Gamma_Catalogo!$C$3:$C$1451,MATCH(Brasil!E3,Gamma_Catalogo!$A$3:$A$1451,0)),"Revisar Ip Code")) | N3: =IF(Brasil!C3="","",IFERROR(INDEX(Gamma_Catalogo!$E$3:$E$1451,MATCH(Brasil!E3,Gamma_Catalogo!$A$3:$A$1451,0)),"Revisar Ip Code")) | O3: =IF(Brasil!C3="","","Brasil")
A4: =IF(Brasil!C4="","",IFERROR(INDEX(Mercados!$C$2:$C$32,MATCH(Brasil!B4,Mercados!$A$2:$A$32,0)),"Revisar Tscode")) | B4: =IF(Brasil!C4="","",Brasil!C4) | C4: =IF(Brasil!C4="","",Brasil!A4) | D4: =IF(Brasil!C4="","",Brasil!E4) | E4: =IF(Brasil!C4="","",Brasil!F4) | F4: =IF(Brasil!C4="","",Brasil!D4) | I4: =IF(Brasil!C4="","",Brasil!H4) | J4: =IF(Brasil!C4="","",Brasil!D4*Brasil!H4) | K4: =IF(Brasil!C4="","","BR") | L4: =IF(Brasil!C4="","",IFERROR(INDEX(Gamma_Catalogo!$D$3:$D$1451,MATCH(Brasil!E4,Gamma_Catalogo!$A$3:$A$1451,0)),"Revisar Ip Code")) | M4: =IF(Brasil!C4="","",IFERROR(INDEX(Gamma_Catalogo!$C$3:$C$1451,MATCH(Brasil!E4,Gamma_Catalogo!$A$3:$A$1451,0)),"Revisar Ip Code")) | N4: =IF(Brasil!C4="","",IFERROR(INDEX(Gamma_Catalogo!$E$3:$E$1451,MATCH(Brasil!E4,Gamma_Catalogo!$A$3:$A$1451,0)),"Revisar Ip Code")) | O4: =IF(Brasil!C4="","","Brasil")
A5: =IF(Brasil!C5="","",IFERROR(INDEX(Mercados!$C$2:$C$32,MATCH(Brasil!B5,Mercados!$A$2:$A$32,0)),"Revisar Tscode")) | B5: =IF(Brasil!C5="","",Brasil!C5) | C5: =IF(Brasil!C5="","",Brasil!A5) | D5: =IF(Brasil!C5="","",Brasil!E5) | E5: =IF(Brasil!C5="","",Brasil!F5) | F5: =IF(Brasil!C5="","",Brasil!D5) | I5: =IF(Brasil!C5="","",Brasil!H5) | J5: =IF(Brasil!C5="","",Brasil!D5*Brasil!H5) | K5: =IF(Brasil!C5="","","BR") | L5: =IF(Brasil!C5="","",IFERROR(INDEX(Gamma_Catalogo!$D$3:$D$1451,MATCH(Brasil!E5,Gamma_Catalogo!$A$3:$A$1451,0)),"Revisar Ip Code")) | M5: =IF(Brasil!C5="","",IFERROR(INDEX(Gamma_Catalogo!$C$3:$C$1451,MATCH(Brasil!E5,Gamma_Catalogo!$A$3:$A$1451,0)),"Revisar Ip Code")) | N5: =IF(Brasil!C5="","",IFERROR(INDEX(Gamma_Catalogo!$E$3:$E$1451,MATCH(Brasil!E5,Gamma_Catalogo!$A$3:$A$1451,0)),"Revisar Ip Code")) | O5: =IF(Brasil!C5="","","Brasil")
A6: =IF(Brasil!C6="","",IFERROR(INDEX(Mercados!$C$2:$C$32,MATCH(Brasil!B6,Mercados!$A$2:$A$32,0)),"Revisar Tscode")) | B6: =IF(Brasil!C6="","",Brasil!C6) | C6: =IF(Brasil!C6="","",Brasil!A6) | D6: =IF(Brasil!C6="","",Brasil!E6) | E6: =IF(Brasil!C6="","",Brasil!F6) | F6: =IF(Brasil!C6="","",Brasil!D6) | I6: =IF(Brasil!C6="","",Brasil!H6) | J6: =IF(Brasil!C6="","",Brasil!D6*Brasil!H6) | K6: =IF(Brasil!C6="","","BR") | L6: =IF(Brasil!C6="","",IFERROR(INDEX(Gamma_Catalogo!$D$3:$D$1451,MATCH(Brasil!E6,Gamma_Catalogo!$A$3:$A$1451,0)),"Revisar Ip Code")) | M6: =IF(Brasil!C6="","",IFERROR(INDEX(Gamma_Catalogo!$C$3:$C$1451,MATCH(Brasil!E6,Gamma_Catalogo!$A$3:$A$1451,0)),"Revisar Ip Code")) | N6: =IF(Brasil!C6="","",IFERROR(INDEX(Gamma_Catalogo!$E$3:$E$1451,MATCH(Brasil!E6,Gamma_Catalogo!$A$3:$A$1451,0)),"Revisar Ip Code")) | O6: =IF(Brasil!C6="","","Brasil")
A7: =IF(Brasil!C7="","",IFERROR(INDEX(Mercados!$C$2:$C$32,MATCH(Brasil!B7,Mercados!$A$2:$A$32,0)),"Revisar Tscode")) | B7: =IF(Brasil!C7="","",Brasil!C7) | C7: =IF(Brasil!C7="","",Brasil!A7) | D7: =IF(Brasil!C7="","",Brasil!E7) | E7: =IF(Brasil!C7="","",Brasil!F7) | F7: =IF(Brasil!C7="","",Brasil!D7) | I7: =IF(Brasil!C7="","",Brasil!H7) | J7: =IF(Brasil!C7="","",Brasil!D7*Brasil!H7) | K7: =IF(Brasil!C7="","","BR") | L7: =IF(Brasil!C7="","",IFERROR(INDEX(Gamma_Catalogo!$D$3:$D$1451,MATCH(Brasil!E7,Gamma_Catalogo!$A$3:$A$1451,0)),"Revisar Ip Code")) | M7: =IF(Brasil!C7="","",IFERROR(INDEX(Gamma_Catalogo!$C$3:$C$1451,MATCH(Brasil!E7,Gamma_Catalogo!$A$3:$A$1451,0)),"Revisar Ip Code")) | N7: =IF(Brasil!C7="","",IFERROR(INDEX(Gamma_Catalogo!$E$3:$E$1451,MATCH(Brasil!E7,Gamma_Catalogo!$A$3:$A$1451,0)),"Revisar Ip Code")) | O7: =IF(Brasil!C7="","","Brasil")
A8: =IF(Brasil!C8="","",IFERROR(INDEX(Mercados!$C$2:$C$32,MATCH(Brasil!B8,Mercados!$A$2:$A$32,0)),"Revisar Tscode")) | B8: =IF(Brasil!C8="","",Brasil!C8) | C8: =IF(Brasil!C8="","",Brasil!A8) | D8: =IF(Brasil!C8="","",Brasil!E8) | E8: =IF(Brasil!C8="","",Brasil!F8) | F8: =IF(Brasil!C8="","",Brasil!D8) | I8: =IF(Brasil!C8="","",Brasil!H8) | J8: =IF(Brasil!C8="","",Brasil!D8*Brasil!H8) | K8: =IF(Brasil!C8="","","BR") | L8: =IF(Brasil!C8="","",IFERROR(INDEX(Gamma_Catalogo!$D$3:$D$1451,MATCH(Brasil!E8,Gamma_Catalogo!$A$3:$A$1451,0)),"Revisar Ip Code")) | M8: =IF(Brasil!C8="","",IFERROR(INDEX(Gamma_Catalogo!$C$3:$C$1451,MATCH(Brasil!E8,Gamma_Catalogo!$A$3:$A$1451,0)),"Revisar Ip Code")) | N8: =IF(Brasil!C8="","",IFERROR(INDEX(Gamma_Catalogo!$E$3:$E$1451,MATCH(Brasil!E8,Gamma_Catalogo!$A$3:$A$1451,0)),"Revisar Ip Code")) | O8: =IF(Brasil!C8="","","Brasil")
A9: =IF(Brasil!C9="","",IFERROR(INDEX(Mercados!$C$2:$C$32,MATCH(Brasil!B9,Mercados!$A$2:$A$32,0)),"Revisar Tscode")) | B9: =IF(Brasil!C9="","",Brasil!C9) | C9: =IF(Brasil!C9="","",Brasil!A9) | D9: =IF(Brasil!C9="","",Brasil!E9) | E9: =IF(Brasil!C9="","",Brasil!F9) | F9: =IF(Brasil!C9="","",Brasil!D9) | I9: =IF(Brasil!C9="","",Brasil!H9) | J9: =IF(Brasil!C9="","",Brasil!D9*Brasil!H9) | K9: =IF(Brasil!C9="","","BR") | L9: =IF(Brasil!C9="","",IFERROR(INDEX(Gamma_Catalogo!$D$3:$D$1451,MATCH(Brasil!E9,Gamma_Catalogo!$A$3:$A$1451,0)),"Revisar Ip Code")) | M9: =IF(Brasil!C9="","",IFERROR(INDEX(Gamma_Catalogo!$C$3:$C$1451,MATCH(Brasil!E9,Gamma_Catalogo!$A$3:$A$1451,0)),"Revisar Ip Code")) | N9: =IF(Brasil!C9="","",IFERROR(INDEX(Gamma_Catalogo!$E$3:$E$1451,MATCH(Brasil!E9,Gamma_Catalogo!$A$3:$A$1451,0)),"Revisar Ip Code")) | O9: =IF(Brasil!C9="","","Brasil")
A10: =IF(Brasil!C10="","",IFERROR(INDEX(Mercados!$C$2:$C$32,MATCH(Brasil!B10,Mercados!$A$2:$A$32,0)),"Revisar Tscode")) | B10: =IF(Brasil!C10="","",Brasil!C10) | C10: =IF(Brasil!C10="","",Brasil!A10) | D10: =IF(Brasil!C10="","",Brasil!E10) | E10: =IF(Brasil!C10="","",Brasil!F10) | F10: =IF(Brasil!C10="","",Brasil!D10) | I10: =IF(Brasil!C10="","",Brasil!H10) | J10: =IF(Brasil!C10="","",Brasil!D10*Brasil!H10) | K10: =IF(Brasil!C10="","","BR") | L10: =IF(Brasil!C10="","",IFERROR(INDEX(Gamma_Catalogo!$D$3:$D$1451,MATCH(Brasil!E10,Gamma_Catalogo!$A$3:$A$1451,0)),"Revisar Ip Code")) | M10: =IF(Brasil!C10="","",IFERROR(INDEX(Gamma_Catalogo!$C$3:$C$1451,MATCH(Brasil!E10,Gamma_Catalogo!$A$3:$A$1451,0)),"Revisar Ip Code")) | N10: =IF(Brasil!C10="","",IFERROR(INDEX(Gamma_Catalogo!$E$3:$E$1451,MATCH(Brasil!E10,Gamma_Catalogo!$A$3:$A$1451,0)),"Revisar Ip Code")) | O10: =IF(Brasil!C10="","","Brasil")
A11: =IF(Brasil!C11="","",IFERROR(INDEX(Mercados!$C$2:$C$32,MATCH(Brasil!B11,Mercados!$A$2:$A$32,0)),"Revisar Tscode")) | B11: =IF(Brasil!C11="","",Brasil!C11) | C11: =IF(Brasil!C11="","",Brasil!A11) | D11: =IF(Brasil!C11="","",Brasil!E11) | E11: =IF(Brasil!C11="","",Brasil!F11) | F11: =IF(Brasil!C11="","",Brasil!D11) | I11: =IF(Brasil!C11="","",Brasil!H11) | J11: =IF(Brasil!C11="","",Brasil!D11*Brasil!H11) | K11: =IF(Brasil!C11="","","BR") | L11: =IF(Brasil!C11="","",IFERROR(INDEX(Gamma_Catalogo!$D$3:$D$1451,MATCH(Brasil!E11,Gamma_Catalogo!$A$3:$A$1451,0)),"Revisar Ip Code")) | M11: =IF(Brasil!C11="","",IFERROR(INDEX(Gamma_Catalogo!$C$3:$C$1451,MATCH(Brasil!E11,Gamma_Catalogo!$A$3:$A$1451,0)),"Revisar Ip Code")) | N11: =IF(Brasil!C11="","",IFERROR(INDEX(Gamma_Catalogo!$E$3:$E$1451,MATCH(Brasil!E11,Gamma_Catalogo!$A$3:$A$1451,0)),"Revisar Ip Code")) | O11: =IF(Brasil!C11="","","Brasil")
A12: =IF(Brasil!C12="","",IFERROR(INDEX(Mercados!$C$2:$C$32,MATCH(Brasil!B12,Mercados!$A$2:$A$32,0)),"Revisar Tscode")) | B12: =IF(Brasil!C12="","",Brasil!C12) | C12: =IF(Brasil!C12="","",Brasil!A12) | D12: =IF(Brasil!C12="","",Brasil!E12) | E12: =IF(Brasil!C12="","",Brasil!F12) | F12: =IF(Brasil!C12="","",Brasil!D12) | I12: =IF(Brasil!C12="","",Brasil!H12) | J12: =IF(Brasil!C12="","",Brasil!D12*Brasil!H12) | K12: =IF(Brasil!C12="","","BR") | L12: =IF(Brasil!C12="","",IFERROR(INDEX(Gamma_Catalogo!$D$3:$D$1451,MATCH(Brasil!E12,Gamma_Catalogo!$A$3:$A$1451,0)),"Revisar Ip Code")) | M12: =IF(Brasil!C12="","",IFERROR(INDEX(Gamma_Catalogo!$C$3:$C$1451,MATCH(Brasil!E12,Gamma_Catalogo!$A$3:$A$1451,0)),"Revisar Ip Code")) | N12: =IF(Brasil!C12="","",IFERROR(INDEX(Gamma_Catalogo!$E$3:$E$1451,MATCH(Brasil!E12,Gamma_Catalogo!$A$3:$A$1451,0)),"Revisar Ip Code")) | O12: =IF(Brasil!C12="","","Brasil")
A13: =IF(Brasil!C13="","",IFERROR(INDEX(Mercados!$C$2:$C$32,MATCH(Brasil!B13,Mercados!$A$2:$A$32,0)),"Revisar Tscode")) | B13: =IF(Brasil!C13="","",Brasil!C13) | C13: =IF(Brasil!C13="","",Brasil!A13) | D13: =IF(Brasil!C13="","",Brasil!E13) | E13: =IF(Brasil!C13="","",Brasil!F13) | F13: =IF(Brasil!C13="","",Brasil!D13) | I13: =IF(Brasil!C13="","",Brasil!H13) | J13: =IF(Brasil!C13="","",Brasil!D13*Brasil!H13) | K13: =IF(Brasil!C13="","","BR") | L13: =IF(Brasil!C13="","",IFERROR(INDEX(Gamma_Catalogo!$D$3:$D$1451,MATCH(Brasil!E13,Gamma_Catalogo!$A$3:$A$1451,0)),"Revisar Ip Code")) | M13: =IF(Brasil!C13="","",IFERROR(INDEX(Gamma_Catalogo!$C$3:$C$1451,MATCH(Brasil!E13,Gamma_Catalogo!$A$3:$A$1451,0)),"Revisar Ip Code")) | N13: =IF(Brasil!C13="","",IFERROR(INDEX(Gamma_Catalogo!$E$3:$E$1451,MATCH(Brasil!E13,Gamma_Catalogo!$A$3:$A$1451,0)),"Revisar Ip Code")) | O13: =IF(Brasil!C13="","","Brasil")
... A651: =IF(Brasil!C651="","",IFERROR(INDEX(Mercados!$C$2:$C$32,MATCH(Brasil!B651,Mercados!$A$2:$A$32,0)),"Revisar Tscode")) | B651: =IF(Brasil!C651="","",Brasil!C651) | C651: =IF(Brasil!C651="","",Brasil!A651) | D651: =IF(Brasil!C651="","",Brasil!E651) | E651: =IF(Brasil!C651="","",Brasil!F651) | F651: =IF(Brasil!C651="","",Brasil!D651) | I651: =IF(Brasil!C651="","",Brasil!H651) | J651: =IF(Brasil!C651="","",Brasil!D651*Brasil!H651) | K651: =IF(Brasil!C651="","","BR") | L651: =IF(Brasil!C651="","",IFERROR(INDEX(Gamma_Catalogo!$D$3:$D$1451,MATCH(Brasil!E651,Gamma_Catalogo!$A$3:$A$1451,0)),"Revisar Ip Code")) | M651: =IF(Brasil!C651="","",IFERROR(INDEX(Gamma_Catalogo!$C$3:$C$1451,MATCH(Brasil!E651,Gamma_Catalogo!$A$3:$A$1451,0)),"Revisar Ip Code")) | N651: =IF(Brasil!C651="","",IFERROR(INDEX(Gamma_Catalogo!$E$3:$E$1451,MATCH(Brasil!E651,Gamma_Catalogo!$A$3:$A$1451,0)),"Revisar Ip Code")) | O651: =IF(Brasil!C651="","","Brasil")
A652: =IF(Suiza_DE_CN_ID!A2="","",IFERROR(INDEX(Mercados!$C$2:$C$32,MATCH(Suiza_DE_CN_ID!B2,Mercados!$A$2:$A$32,0)),"Revisar Tscode")) -> 773 - COLOMBIA | B652: =IF(Suiza_DE_CN_ID!A2="","",Suiza_DE_CN_ID!A2) -> akt | C652: =IF(Suiza_DE_CN_ID!A2="","",Suiza_DE_CN_ID!C2) -> 1730134137 | D652: =IF(Suiza_DE_CN_ID!A2="","",Suiza_DE_CN_ID!D2) -> 2283700 | E652: =IF(Suiza_DE_CN_ID!A2="","",Suiza_DE_CN_ID!E2) -> 180/55ZR17M/CTL (73W)(M) Z8-R | F652: =IF(Suiza_DE_CN_ID!A2="","",Suiza_DE_CN_ID!G2) -> 3 | I652: =IF(Suiza_DE_CN_ID!A2="","",Suiza_DE_CN_ID!H2) -> 102 | J652: =IF(Suiza_DE_CN_ID!A2="","",Suiza_DE_CN_ID!I2) -> 327.3 | K652: =IF(Suiza_DE_CN_ID!A2="","",UPPER(Suiza_DE_CN_ID!J2)) -> CN | L652: =IF(Suiza_DE_CN_ID!A2="","",IFERROR(INDEX(Gamma_Catalogo!$D$3:$D$1451,MATCH(Suiza_DE_CN_ID!D2,Gamma_Catalogo!$A$3:$A$1451,0)),"Revisar Ip Code")) -> RADIAL ZR | M652: =IF(Suiza_DE_CN_ID!A2="","",IFERROR(INDEX(Gamma_Catalogo!$C$3:$C$1451,MATCH(Suiza_DE_CN_ID!D2,Gamma_Catalogo!$A$3:$A$1451,0)),"Revisar Ip Code")) -> R | N652: =IF(Suiza_DE_CN_ID!A2="","",IFERROR(INDEX(Gamma_Catalogo!$E$3:$E$1451,MATCH(Suiza_DE_CN_ID!D2,Gamma_Catalogo!$A$3:$A$1451,0)),"Revisar Ip Code")) -> SPORT TOURING RADIAL | O652: =IF(Suiza_DE_CN_ID!A2="","","Suiza") -> Suiza
A653: =IF(Suiza_DE_CN_ID!A3="","",IFERROR(INDEX(Mercados!$C$2:$C$32,MATCH(Suiza_DE_CN_ID!B3,Mercados!$A$2:$A$32,0)),"Revisar Tscode")) | B653: =IF(Suiza_DE_CN_ID!A3="","",Suiza_DE_CN_ID!A3) | C653: =IF(Suiza_DE_CN_ID!A3="","",Suiza_DE_CN_ID!C3) | D653: =IF(Suiza_DE_CN_ID!A3="","",Suiza_DE_CN_ID!D3) | E653: =IF(Suiza_DE_CN_ID!A3="","",Suiza_DE_CN_ID!E3) | F653: =IF(Suiza_DE_CN_ID!A3="","",Suiza_DE_CN_ID!G3) | I653: =IF(Suiza_DE_CN_ID!A3="","",Suiza_DE_CN_ID!H3) | J653: =IF(Suiza_DE_CN_ID!A3="","",Suiza_DE_CN_ID!I3) | K653: =IF(Suiza_DE_CN_ID!A3="","",UPPER(Suiza_DE_CN_ID!J3)) | L653: =IF(Suiza_DE_CN_ID!A3="","",IFERROR(INDEX(Gamma_Catalogo!$D$3:$D$1451,MATCH(Suiza_DE_CN_ID!D3,Gamma_Catalogo!$A$3:$A$1451,0)),"Revisar Ip Code")) | M653: =IF(Suiza_DE_CN_ID!A3="","",IFERROR(INDEX(Gamma_Catalogo!$C$3:$C$1451,MATCH(Suiza_DE_CN_ID!D3,Gamma_Catalogo!$A$3:$A$1451,0)),"Revisar Ip Code")) | N653: =IF(Suiza_DE_CN_ID!A3="","",IFERROR(INDEX(Gamma_Catalogo!$E$3:$E$1451,MATCH(Suiza_DE_CN_ID!D3,Gamma_Catalogo!$A$3:$A$1451,0)),"Revisar Ip Code")) | O653: =IF(Suiza_DE_CN_ID!A3="","","Suiza")
A654: =IF(Suiza_DE_CN_ID!A4="","",IFERROR(INDEX(Mercados!$C$2:$C$32,MATCH(Suiza_DE_CN_ID!B4,Mercados!$A$2:$A$32,0)),"Revisar Tscode")) | B654: =IF(Suiza_DE_CN_ID!A4="","",Suiza_DE_CN_ID!A4) | C654: =IF(Suiza_DE_CN_ID!A4="","",Suiza_DE_CN_ID!C4) | D654: =IF(Suiza_DE_CN_ID!A4="","",Suiza_DE_CN_ID!D4) | E654: =IF(Suiza_DE_CN_ID!A4="","",Suiza_DE_CN_ID!E4) | F654: =IF(Suiza_DE_CN_ID!A4="","",Suiza_DE_CN_ID!G4) | I654: =IF(Suiza_DE_CN_ID!A4="","",Suiza_DE_CN_ID!H4) | J654: =IF(Suiza_DE_CN_ID!A4="","",Suiza_DE_CN_ID!I4) | K654: =IF(Suiza_DE_CN_ID!A4="","",UPPER(Suiza_DE_CN_ID!J4)) | L654: =IF(Suiza_DE_CN_ID!A4="","",IFERROR(INDEX(Gamma_Catalogo!$D$3:$D$1451,MATCH(Suiza_DE_CN_ID!D4,Gamma_Catalogo!$A$3:$A$1451,0)),"Revisar Ip Code")) | M654: =IF(Suiza_DE_CN_ID!A4="","",IFERROR(INDEX(Gamma_Catalogo!$C$3:$C$1451,MATCH(Suiza_DE_CN_ID!D4,Gamma_Catalogo!$A$3:$A$1451,0)),"Revisar Ip Code")) | N654: =IF(Suiza_DE_CN_ID!A4="","",IFERROR(INDEX(Gamma_Catalogo!$E$3:$E$1451,MATCH(Suiza_DE_CN_ID!D4,Gamma_Catalogo!$A$3:$A$1451,0)),"Revisar Ip Code")) | O654: =IF(Suiza_DE_CN_ID!A4="","","Suiza")
A655: =IF(Suiza_DE_CN_ID!A5="","",IFERROR(INDEX(Mercados!$C$2:$C$32,MATCH(Suiza_DE_CN_ID!B5,Mercados!$A$2:$A$32,0)),"Revisar Tscode")) | B655: =IF(Suiza_DE_CN_ID!A5="","",Suiza_DE_CN_ID!A5) | C655: =IF(Suiza_DE_CN_ID!A5="","",Suiza_DE_CN_ID!C5) | D655: =IF(Suiza_DE_CN_ID!A5="","",Suiza_DE_CN_ID!D5) | E655: =IF(Suiza_DE_CN_ID!A5="","",Suiza_DE_CN_ID!E5) | F655: =IF(Suiza_DE_CN_ID!A5="","",Suiza_DE_CN_ID!G5) | I655: =IF(Suiza_DE_CN_ID!A5="","",Suiza_DE_CN_ID!H5) | J655: =IF(Suiza_DE_CN_ID!A5="","",Suiza_DE_CN_ID!I5) | K655: =IF(Suiza_DE_CN_ID!A5="","",UPPER(Suiza_DE_CN_ID!J5)) | L655: =IF(Suiza_DE_CN_ID!A5="","",IFERROR(INDEX(Gamma_Catalogo!$D$3:$D$1451,MATCH(Suiza_DE_CN_ID!D5,Gamma_Catalogo!$A$3:$A$1451,0)),"Revisar Ip Code")) | M655: =IF(Suiza_DE_CN_ID!A5="","",IFERROR(INDEX(Gamma_Catalogo!$C$3:$C$1451,MATCH(Suiza_DE_CN_ID!D5,Gamma_Catalogo!$A$3:$A$1451,0)),"Revisar Ip Code")) | N655: =IF(Suiza_DE_CN_ID!A5="","",IFERROR(INDEX(Gamma_Catalogo!$E$3:$E$1451,MATCH(Suiza_DE_CN_ID!D5,Gamma_Catalogo!$A$3:$A$1451,0)),"Revisar Ip Code")) | O655: =IF(Suiza_DE_CN_ID!A5="","","Suiza")
A656: =IF(Suiza_DE_CN_ID!A6="","",IFERROR(INDEX(Mercados!$C$2:$C$32,MATCH(Suiza_DE_CN_ID!B6,Mercados!$A$2:$A$32,0)),"Revisar Tscode")) | B656: =IF(Suiza_DE_CN_ID!A6="","",Suiza_DE_CN_ID!A6) | C656: =IF(Suiza_DE_CN_ID!A6="","",Suiza_DE_CN_ID!C6) | D656: =IF(Suiza_DE_CN_ID!A6="","",Suiza_DE_CN_ID!D6) | E656: =IF(Suiza_DE_CN_ID!A6="","",Suiza_DE_CN_ID!E6) | F656: =IF(Suiza_DE_CN_ID!A6="","",Suiza_DE_CN_ID!G6) | I656: =IF(Suiza_DE_CN_ID!A6="","",Suiza_DE_CN_ID!H6) | J656: =IF(Suiza_DE_CN_ID!A6="","",Suiza_DE_CN_ID!I6) | K656: =IF(Suiza_DE_CN_ID!A6="","",UPPER(Suiza_DE_CN_ID!J6)) | L656: =IF(Suiza_DE_CN_ID!A6="","",IFERROR(INDEX(Gamma_Catalogo!$D$3:$D$1451,MATCH(Suiza_DE_CN_ID!D6,Gamma_Catalogo!$A$3:$A$1451,0)),"Revisar Ip Code")) | M656: =IF(Suiza_DE_CN_ID!A6="","",IFERROR(INDEX(Gamma_Catalogo!$C$3:$C$1451,MATCH(Suiza_DE_CN_ID!D6,Gamma_Catalogo!$A$3:$A$1451,0)),"Revisar Ip Code")) | N656: =IF(Suiza_DE_CN_ID!A6="","",IFERROR(INDEX(Gamma_Catalogo!$E$3:$E$1451,MATCH(Suiza_DE_CN_ID!D6,Gamma_Catalogo!$A$3:$A$1451,0)),"Revisar Ip Code")) | O656: =IF(Suiza_DE_CN_ID!A6="","","Suiza")
A657: =IF(Suiza_DE_CN_ID!A7="","",IFERROR(INDEX(Mercados!$C$2:$C$32,MATCH(Suiza_DE_CN_ID!B7,Mercados!$A$2:$A$32,0)),"Revisar Tscode")) | B657: =IF(Suiza_DE_CN_ID!A7="","",Suiza_DE_CN_ID!A7) | C657: =IF(Suiza_DE_CN_ID!A7="","",Suiza_DE_CN_ID!C7) | D657: =IF(Suiza_DE_CN_ID!A7="","",Suiza_DE_CN_ID!D7) | E657: =IF(Suiza_DE_CN_ID!A7="","",Suiza_DE_CN_ID!E7) | F657: =IF(Suiza_DE_CN_ID!A7="","",Suiza_DE_CN_ID!G7) | I657: =IF(Suiza_DE_CN_ID!A7="","",Suiza_DE_CN_ID!H7) | J657: =IF(Suiza_DE_CN_ID!A7="","",Suiza_DE_CN_ID!I7) | K657: =IF(Suiza_DE_CN_ID!A7="","",UPPER(Suiza_DE_CN_ID!J7)) | L657: =IF(Suiza_DE_CN_ID!A7="","",IFERROR(INDEX(Gamma_Catalogo!$D$3:$D$1451,MATCH(Suiza_DE_CN_ID!D7,Gamma_Catalogo!$A$3:$A$1451,0)),"Revisar Ip Code")) | M657: =IF(Suiza_DE_CN_ID!A7="","",IFERROR(INDEX(Gamma_Catalogo!$C$3:$C$1451,MATCH(Suiza_DE_CN_ID!D7,Gamma_Catalogo!$A$3:$A$1451,0)),"Revisar Ip Code")) | N657: =IF(Suiza_DE_CN_ID!A7="","",IFERROR(INDEX(Gamma_Catalogo!$E$3:$E$1451,MATCH(Suiza_DE_CN_ID!D7,Gamma_Catalogo!$A$3:$A$1451,0)),"Revisar Ip Code")) | O657: =IF(Suiza_DE_CN_ID!A7="","","Suiza")
A658: =IF(Suiza_DE_CN_ID!A8="","",IFERROR(INDEX(Mercados!$C$2:$C$32,MATCH(Suiza_DE_CN_ID!B8,Mercados!$A$2:$A$32,0)),"Revisar Tscode")) | B658: =IF(Suiza_DE_CN_ID!A8="","",Suiza_DE_CN_ID!A8) | C658: =IF(Suiza_DE_CN_ID!A8="","",Suiza_DE_CN_ID!C8) | D658: =IF(Suiza_DE_CN_ID!A8="","",Suiza_DE_CN_ID!D8) | E658: =IF(Suiza_DE_CN_ID!A8="","",Suiza_DE_CN_ID!E8) | F658: =IF(Suiza_DE_CN_ID!A8="","",Suiza_DE_CN_ID!G8) | I658: =IF(Suiza_DE_CN_ID!A8="","",Suiza_DE_CN_ID!H8) | J658: =IF(Suiza_DE_CN_ID!A8="","",Suiza_DE_CN_ID!I8) | K658: =IF(Suiza_DE_CN_ID!A8="","",UPPER(Suiza_DE_CN_ID!J8)) | L658: =IF(Suiza_DE_CN_ID!A8="","",IFERROR(INDEX(Gamma_Catalogo!$D$3:$D$1451,MATCH(Suiza_DE_CN_ID!D8,Gamma_Catalogo!$A$3:$A$1451,0)),"Revisar Ip Code")) | M658: =IF(Suiza_DE_CN_ID!A8="","",IFERROR(INDEX(Gamma_Catalogo!$C$3:$C$1451,MATCH(Suiza_DE_CN_ID!D8,Gamma_Catalogo!$A$3:$A$1451,0)),"Revisar Ip Code")) | N658: =IF(Suiza_DE_CN_ID!A8="","",IFERROR(INDEX(Gamma_Catalogo!$E$3:$E$1451,MATCH(Suiza_DE_CN_ID!D8,Gamma_Catalogo!$A$3:$A$1451,0)),"Revisar Ip Code")) | O658: =IF(Suiza_DE_CN_ID!A8="","","Suiza")
A659: =IF(Suiza_DE_CN_ID!A9="","",IFERROR(INDEX(Mercados!$C$2:$C$32,MATCH(Suiza_DE_CN_ID!B9,Mercados!$A$2:$A$32,0)),"Revisar Tscode")) | B659: =IF(Suiza_DE_CN_ID!A9="","",Suiza_DE_CN_ID!A9) | C659: =IF(Suiza_DE_CN_ID!A9="","",Suiza_DE_CN_ID!C9) | D659: =IF(Suiza_DE_CN_ID!A9="","",Suiza_DE_CN_ID!D9) | E659: =IF(Suiza_DE_CN_ID!A9="","",Suiza_DE_CN_ID!E9) | F659: =IF(Suiza_DE_CN_ID!A9="","",Suiza_DE_CN_ID!G9) | I659: =IF(Suiza_DE_CN_ID!A9="","",Suiza_DE_CN_ID!H9) | J659: =IF(Suiza_DE_CN_ID!A9="","",Suiza_DE_CN_ID!I9) | K659: =IF(Suiza_DE_CN_ID!A9="","",UPPER(Suiza_DE_CN_ID!J9)) | L659: =IF(Suiza_DE_CN_ID!A9="","",IFERROR(INDEX(Gamma_Catalogo!$D$3:$D$1451,MATCH(Suiza_DE_CN_ID!D9,Gamma_Catalogo!$A$3:$A$1451,0)),"Revisar Ip Code")) | M659: =IF(Suiza_DE_CN_ID!A9="","",IFERROR(INDEX(Gamma_Catalogo!$C$3:$C$1451,MATCH(Suiza_DE_CN_ID!D9,Gamma_Catalogo!$A$3:$A$1451,0)),"Revisar Ip Code")) | N659: =IF(Suiza_DE_CN_ID!A9="","",IFERROR(INDEX(Gamma_Catalogo!$E$3:$E$1451,MATCH(Suiza_DE_CN_ID!D9,Gamma_Catalogo!$A$3:$A$1451,0)),"Revisar Ip Code")) | O659: =IF(Suiza_DE_CN_ID!A9="","","Suiza")
A660: =IF(Suiza_DE_CN_ID!A10="","",IFERROR(INDEX(Mercados!$C$2:$C$32,MATCH(Suiza_DE_CN_ID!B10,Mercados!$A$2:$A$32,0)),"Revisar Tscode")) | B660: =IF(Suiza_DE_CN_ID!A10="","",Suiza_DE_CN_ID!A10) | C660: =IF(Suiza_DE_CN_ID!A10="","",Suiza_DE_CN_ID!C10) | D660: =IF(Suiza_DE_CN_ID!A10="","",Suiza_DE_CN_ID!D10) | E660: =IF(Suiza_DE_CN_ID!A10="","",Suiza_DE_CN_ID!E10) | F660: =IF(Suiza_DE_CN_ID!A10="","",Suiza_DE_CN_ID!G10) | I660: =IF(Suiza_DE_CN_ID!A10="","",Suiza_DE_CN_ID!H10) | J660: =IF(Suiza_DE_CN_ID!A10="","",Suiza_DE_CN_ID!I10) | K660: =IF(Suiza_DE_CN_ID!A10="","",UPPER(Suiza_DE_CN_ID!J10)) | L660: =IF(Suiza_DE_CN_ID!A10="","",IFERROR(INDEX(Gamma_Catalogo!$D$3:$D$1451,MATCH(Suiza_DE_CN_ID!D10,Gamma_Catalogo!$A$3:$A$1451,0)),"Revisar Ip Code")) | M660: =IF(Suiza_DE_CN_ID!A10="","",IFERROR(INDEX(Gamma_Catalogo!$C$3:$C$1451,MATCH(Suiza_DE_CN_ID!D10,Gamma_Catalogo!$A$3:$A$1451,0)),"Revisar Ip Code")) | N660: =IF(Suiza_DE_CN_ID!A10="","",IFERROR(INDEX(Gamma_Catalogo!$E$3:$E$1451,MATCH(Suiza_DE_CN_ID!D10,Gamma_Catalogo!$A$3:$A$1451,0)),"Revisar Ip Code")) | O660: =IF(Suiza_DE_CN_ID!A10="","","Suiza")
A661: =IF(Suiza_DE_CN_ID!A11="","",IFERROR(INDEX(Mercados!$C$2:$C$32,MATCH(Suiza_DE_CN_ID!B11,Mercados!$A$2:$A$32,0)),"Revisar Tscode")) | B661: =IF(Suiza_DE_CN_ID!A11="","",Suiza_DE_CN_ID!A11) | C661: =IF(Suiza_DE_CN_ID!A11="","",Suiza_DE_CN_ID!C11) | D661: =IF(Suiza_DE_CN_ID!A11="","",Suiza_DE_CN_ID!D11) | E661: =IF(Suiza_DE_CN_ID!A11="","",Suiza_DE_CN_ID!E11) | F661: =IF(Suiza_DE_CN_ID!A11="","",Suiza_DE_CN_ID!G11) | I661: =IF(Suiza_DE_CN_ID!A11="","",Suiza_DE_CN_ID!H11) | J661: =IF(Suiza_DE_CN_ID!A11="","",Suiza_DE_CN_ID!I11) | K661: =IF(Suiza_DE_CN_ID!A11="","",UPPER(Suiza_DE_CN_ID!J11)) | L661: =IF(Suiza_DE_CN_ID!A11="","",IFERROR(INDEX(Gamma_Catalogo!$D$3:$D$1451,MATCH(Suiza_DE_CN_ID!D11,Gamma_Catalogo!$A$3:$A$1451,0)),"Revisar Ip Code")) | M661: =IF(Suiza_DE_CN_ID!A11="","",IFERROR(INDEX(Gamma_Catalogo!$C$3:$C$1451,MATCH(Suiza_DE_CN_ID!D11,Gamma_Catalogo!$A$3:$A$1451,0)),"Revisar Ip Code")) | N661: =IF(Suiza_DE_CN_ID!A11="","",IFERROR(INDEX(Gamma_Catalogo!$E$3:$E$1451,MATCH(Suiza_DE_CN_ID!D11,Gamma_Catalogo!$A$3:$A$1451,0)),"Revisar Ip Code")) | O661: =IF(Suiza_DE_CN_ID!A11="","","Suiza")
A662: =IF(Suiza_DE_CN_ID!A12="","",IFERROR(INDEX(Mercados!$C$2:$C$32,MATCH(Suiza_DE_CN_ID!B12,Mercados!$A$2:$A$32,0)),"Revisar Tscode")) | B662: =IF(Suiza_DE_CN_ID!A12="","",Suiza_DE_CN_ID!A12) | C662: =IF(Suiza_DE_CN_ID!A12="","",Suiza_DE_CN_ID!C12) | D662: =IF(Suiza_DE_CN_ID!A12="","",Suiza_DE_CN_ID!D12) | E662: =IF(Suiza_DE_CN_ID!A12="","",Suiza_DE_CN_ID!E12) | F662: =IF(Suiza_DE_CN_ID!A12="","",Suiza_DE_CN_ID!G12) | I662: =IF(Suiza_DE_CN_ID!A12="","",Suiza_DE_CN_ID!H12) | J662: =IF(Suiza_DE_CN_ID!A12="","",Suiza_DE_CN_ID!I12) | K662: =IF(Suiza_DE_CN_ID!A12="","",UPPER(Suiza_DE_CN_ID!J12)) | L662: =IF(Suiza_DE_CN_ID!A12="","",IFERROR(INDEX(Gamma_Catalogo!$D$3:$D$1451,MATCH(Suiza_DE_CN_ID!D12,Gamma_Catalogo!$A$3:$A$1451,0)),"Revisar Ip Code")) | M662: =IF(Suiza_DE_CN_ID!A12="","",IFERROR(INDEX(Gamma_Catalogo!$C$3:$C$1451,MATCH(Suiza_DE_CN_ID!D12,Gamma_Catalogo!$A$3:$A$1451,0)),"Revisar Ip Code")) | N662: =IF(Suiza_DE_CN_ID!A12="","",IFERROR(INDEX(Gamma_Catalogo!$E$3:$E$1451,MATCH(Suiza_DE_CN_ID!D12,Gamma_Catalogo!$A$3:$A$1451,0)),"Revisar Ip Code")) | O662: =IF(Suiza_DE_CN_ID!A12="","","Suiza")
A663: =IF(Suiza_DE_CN_ID!A13="","",IFERROR(INDEX(Mercados!$C$2:$C$32,MATCH(Suiza_DE_CN_ID!B13,Mercados!$A$2:$A$32,0)),"Revisar Tscode")) | B663: =IF(Suiza_DE_CN_ID!A13="","",Suiza_DE_CN_ID!A13) | C663: =IF(Suiza_DE_CN_ID!A13="","",Suiza_DE_CN_ID!C13) | D663: =IF(Suiza_DE_CN_ID!A13="","",Suiza_DE_CN_ID!D13) | E663: =IF(Suiza_DE_CN_ID!A13="","",Suiza_DE_CN_ID!E13) | F663: =IF(Suiza_DE_CN_ID!A13="","",Suiza_DE_CN_ID!G13) | I663: =IF(Suiza_DE_CN_ID!A13="","",Suiza_DE_CN_ID!H13) | J663: =IF(Suiza_DE_CN_ID!A13="","",Suiza_DE_CN_ID!I13) | K663: =IF(Suiza_DE_CN_ID!A13="","",UPPER(Suiza_DE_CN_ID!J13)) | L663: =IF(Suiza_DE_CN_ID!A13="","",IFERROR(INDEX(Gamma_Catalogo!$D$3:$D$1451,MATCH(Suiza_DE_CN_ID!D13,Gamma_Catalogo!$A$3:$A$1451,0)),"Revisar Ip Code")) | M663: =IF(Suiza_DE_CN_ID!A13="","",IFERROR(INDEX(Gamma_Catalogo!$C$3:$C$1451,MATCH(Suiza_DE_CN_ID!D13,Gamma_Catalogo!$A$3:$A$1451,0)),"Revisar Ip Code")) | N663: =IF(Suiza_DE_CN_ID!A13="","",IFERROR(INDEX(Gamma_Catalogo!$E$3:$E$1451,MATCH(Suiza_DE_CN_ID!D13,Gamma_Catalogo!$A$3:$A$1451,0)),"Revisar Ip Code")) | O663: =IF(Suiza_DE_CN_ID!A13="","","Suiza")
... A1101: =IF(Suiza_DE_CN_ID!A451="","",IFERROR(INDEX(Mercados!$C$2:$C$32,MATCH(Suiza_DE_CN_ID!B451,Mercados!$A$2:$A$32,0)),"Revisar Tscode")) | B1101: =IF(Suiza_DE_CN_ID!A451="","",Suiza_DE_CN_ID!A451) | C1101: =IF(Suiza_DE_CN_ID!A451="","",Suiza_DE_CN_ID!C451) | D1101: =IF(Suiza_DE_CN_ID!A451="","",Suiza_DE_CN_ID!D451) | E1101: =IF(Suiza_DE_CN_ID!A451="","",Suiza_DE_CN_ID!E451) | F1101: =IF(Suiza_DE_CN_ID!A451="","",Suiza_DE_CN_ID!G451) | I1101: =IF(Suiza_DE_CN_ID!A451="","",Suiza_DE_CN_ID!H451) | J1101: =IF(Suiza_DE_CN_ID!A451="","",Suiza_DE_CN_ID!I451) | K1101: =IF(Suiza_DE_CN_ID!A451="","",UPPER(Suiza_DE_CN_ID!J451)) | L1101: =IF(Suiza_DE_CN_ID!A451="","",IFERROR(INDEX(Gamma_Catalogo!$D$3:$D$1451,MATCH(Suiza_DE_CN_ID!D451,Gamma_Catalogo!$A$3:$A$1451,0)),"Revisar Ip Code")) | M1101: =IF(Suiza_DE_CN_ID!A451="","",IFERROR(INDEX(Gamma_Catalogo!$C$3:$C$1451,MATCH(Suiza_DE_CN_ID!D451,Gamma_Catalogo!$A$3:$A$1451,0)),"Revisar Ip Code")) | N1101: =IF(Suiza_DE_CN_ID!A451="","",IFERROR(INDEX(Gamma_Catalogo!$E$3:$E$1451,MATCH(Suiza_DE_CN_ID!D451,Gamma_Catalogo!$A$3:$A$1451,0)),"Revisar Ip Code")) | O1101: =IF(Suiza_DE_CN_ID!A451="","","Suiza")
